tr55/__init__.py
tr55/compareMiniAppTables.py
tr55/makeMiniAppTable.py
tr55/model.py
tr55/operations.py
tr55/tablelookup.py
tr55/tables.py
tr55/water_quality.py
tr55-1.3.0.dist-info/top_level.txt
tr55-1.3.0.dist-info/METADATA
tr55-1.3.0.dist-info/DESCRIPTION.rst
tr55-1.3.0.dist-info/metadata.json
tr55-1.3.0.dist-info/WHEEL
tr55-1.3.0.dist-info/RECORD
