Metadata-Version: 2.0
Name: tr55
Version: 1.3.0
Summary: A Python implementation of TR-55.
Home-page: https://github.com/azavea/tr-55
Author: Azavea Inc.
Author-email: UNKNOWN
License: Apache License 2.0
Keywords: tr-55 watershed hydrology
Platform: UNKNOWN
Classifier: Development Status :: 1 - Planning
Classifier: Intended Audience :: Developers
Classifier: Intended Audience :: Education
Classifier: License :: OSI Approved :: Apache Software License
Classifier: Programming Language :: Python :: 2
Classifier: Programming Language :: Python :: 3
Provides-Extra: dev
Provides-Extra: test
Requires-Dist: nose (>=1.3.4); extra == 'test'
